portabletext_html/__init__.py
portabletext_html/constants.py
portabletext_html/logger.py
portabletext_html/marker_definitions.py
portabletext_html/py.typed
portabletext_html/renderer.py
portabletext_html/types.py
portabletext_html/utils.py
portabletext_html-1.1.3.dist-info/LICENSE
portabletext_html-1.1.3.dist-info/WHEEL
portabletext_html-1.1.3.dist-info/METADATA
portabletext_html-1.1.3.dist-info/RECORD
