Metadata-Version: 2.1
Name: portabletext-html
Version: 1.1.3
Summary: HTML renderer for Sanity's Portable Text format
Home-page: https://github.com/otovo/python-sanity-html
License: Apache2
Keywords: sanity,portable,text,html,parsing
Author: Kristian Klette
Author-email: klette@otovo.com
Maintainer: Sondre Lillebø Gundersen
Maintainer-email: sondrelg@live.no
Requires-Python: >=3.7,<4.0
Classifier: Development Status :: 5 - Production/Stable
Classifier: Environment :: Web Environment
Classifier: Intended Audience :: Developers
Classifier: License :: OSI Approved :: Apache Software License
Classifier: License :: Other/Proprietary License
Classifier: Operating System :: OS Independent
Classifier: Programming Language :: Python
Classifier: Programming Language :: Python :: 3
Classifier: Programming Language :: Python :: 3.10
Classifier: Programming Language :: Python :: 3.7
Classifier: Programming Language :: Python :: 3.8
Classifier: Programming Language :: Python :: 3.9
Classifier: Topic :: Text Processing
Classifier: Topic :: Text Processing :: Markup
Classifier: Topic :: Text Processing :: Markup :: HTML
Classifier: Typing :: Typed
Project-URL: Repository, https://github.com/otovo/python-sanity-html
